wepay/__init__.py
wepay/api.py
wepay/exceptions.py
wepay-0.3.4.dist-info/LICENSE
wepay-0.3.4.dist-info/METADATA
wepay-0.3.4.dist-info/WHEEL
wepay-0.3.4.dist-info/top_level.txt
wepay-0.3.4.dist-info/RECORD
