Metadata-Version: 2.1
Name: wepay
Version: 0.3.4
Summary: A Python SDK for our WePay API.
Home-page: https://github.com/wepay/Python-SDK
Author: WePay API Team
Author-email: api@wepay.com
License: MIT License
Platform: any
Classifier: Development Status :: 4 - Beta
Classifier: Intended Audience :: Developers
Classifier: License :: OSI Approved :: MIT License
Classifier: Natural Language :: English
Classifier: Operating System :: OS Independent
Classifier: Programming Language :: Python
Requires-Dist: requests (==2.2.1)
